python_embeddings/__init__.py
python_embeddings/chroma_play.py
python_embeddings/cli_utils.py
python_embeddings/code_parsers.py
python_embeddings/git_utils.py
python_embeddings/image_tests.py
python_embeddings/log_utils.py
python_embeddings/search.py
python_embeddings/sync_repo.py
python_embeddings/vector_db.py
python_embeddings-0.1.0.dist-info/LICENSE
python_embeddings-0.1.0.dist-info/METADATA
python_embeddings-0.1.0.dist-info/WHEEL
python_embeddings-0.1.0.dist-info/entry_points.txt
python_embeddings-0.1.0.dist-info/top_level.txt
python_embeddings-0.1.0.dist-info/RECORD
